omnigraph/__init__.py
omnigraph/basecmd.py
omnigraph/ominigraph_paths.py
omnigraph/omnigraph_cmd.py
omnigraph/omniserver.py
omnigraph/rdf_dataset.py
omnigraph/rdfdump.py
omnigraph/rdfdump_cmd.py
omnigraph/server_config.py
omnigraph/software.py
omnigraph/sparql_server.py
omnigraph/version.py
omnigraph/resources/__init__.py
omnigraph/resources/examples/datasets.yaml
omnigraph/resources/examples/endpoints.yaml
omnigraph/resources/examples/prefixes.yaml
omnigraph/resources/examples/queries.yaml
omnigraph/resources/examples/royals.ttl
omnigraph/resources/examples/servers.yaml
omnigraph/servers/__init__.py
omnigraph/servers/blazegraph.py
omnigraph/servers/graphdb.py
omnigraph/servers/jena.py
omnigraph/servers/oxigraph.py
omnigraph/servers/qlever.py
omnigraph/servers/stardog.py
omnigraph/servers/virtuoso.py
pyomnigraph-0.1.0.dist-info/METADATA
pyomnigraph-0.1.0.dist-info/WHEEL
pyomnigraph-0.1.0.dist-info/entry_points.txt
pyomnigraph-0.1.0.dist-info/licenses/LICENSE
pyomnigraph-0.1.0.dist-info/RECORD
