Metadata-Version: 2.4
Name: pyomnigraph
Version: 0.1.0
Summary: pyomnigraph: Unified Python interface for multiple graph databases (SPARQL, Neo4j, Weaviate)
Project-URL: Home, https://github.com/WolfgangFahl/omnigraph
Project-URL: Documentation, https://wiki.bitplan.com/index.php/omnigraph
Project-URL: Source, https://github.com/WolfgangFahl/omnigraph
Author-email: Wolfgang Fahl <wf@WolfgangFahl.com>
Maintainer-email: Wolfgang Fahl <wf@WolfgangFahl.com>
License: Apache-2.0
License-File: LICENSE
Keywords: SPARQL,blazegraph,database,graph,jena,neo4j,qlever,rdf,virtuoso,weaviate
Classifier: Development Status :: 4 - Beta
Classifier: Environment :: Web Environment
Classifier: Intended Audience :: Developers
Classifier: Intended Audience :: Science/Research
Classifier: License :: OSI Approved :: Apache Software License
Classifier: Operating System :: OS Independent
Classifier: Programming Language :: Python :: 3 :: Only
Classifier: Programming Language :: Python :: 3.10
Classifier: Programming Language :: Python :: 3.11
Classifier: Programming Language :: Python :: 3.12
Classifier: Programming Language :: Python :: 3.13
Classifier: Topic :: Database
Classifier: Topic :: Software Development :: Libraries :: Python Modules
Requires-Python: >=3.10
Requires-Dist: dacite>=1.8.1
Requires-Dist: dataclasses-json>=0.6.3
Requires-Dist: psutil>=7.0.0
Requires-Dist: pybasemkit>=0.1.0
Requires-Dist: pylodstorage>=0.17.0
Requires-Dist: pyyaml>=6.0.1
Requires-Dist: tabulate>=0.9.0
Requires-Dist: tdqm
Provides-Extra: dev
Requires-Dist: black>=23.0.0; extra == 'dev'
Requires-Dist: isort>=5.12.0; extra == 'dev'
Requires-Dist: mypy>=1.0.0; extra == 'dev'
Requires-Dist: pre-commit>=3.0.0; extra == 'dev'
Provides-Extra: test
Requires-Dist: green; extra == 'test'
Requires-Dist: pytest-asyncio>=0.21.0; extra == 'test'
Requires-Dist: pytest>=7.0.0; extra == 'test'
